werkzeug_rfc7xx/__init__.py
werkzeug_rfc7xx-1.1.0.dist-info/AUTHORS.rst
werkzeug_rfc7xx-1.1.0.dist-info/LICENSE
werkzeug_rfc7xx-1.1.0.dist-info/METADATA
werkzeug_rfc7xx-1.1.0.dist-info/WHEEL
werkzeug_rfc7xx-1.1.0.dist-info/top_level.txt
werkzeug_rfc7xx-1.1.0.dist-info/RECORD
